NSE_STOCK_LOAD/Data_backup.py
NSE_STOCK_LOAD/TablesMetadata.txt
NSE_STOCK_LOAD/__init__.py
NSE_STOCK_LOAD/diff.txt
NSE_STOCK_LOAD/env_setup.py
NSE_STOCK_LOAD/export.txt
NSE_STOCK_LOAD/get_files.py
NSE_STOCK_LOAD/load_activestock.py
NSE_STOCK_LOAD/load_daily_data.py
NSE_STOCK_LOAD/load_my_stock_details.py
NSE_STOCK_LOAD/load_nse_indices.py
NSE_STOCK_LOAD/load_stock_status_table.py
NSE_STOCK_LOAD/load_stockcode.py
NSE_STOCK_LOAD/loghandler.py
NSE_STOCK_LOAD/mail.py
NSE_STOCK_LOAD/mime_dict.py
NSE_STOCK_LOAD/purge_files.py
NSE_STOCK_LOAD/reports.py
NSE_STOCK_LOAD/requirements.txt
NSE_STOCK_LOAD/sequence.py
NSE_STOCK_LOAD/stock_code_check.py
NSE_STOCK_LOAD/stockcode.txt
NSE_STOCK_LOAD/tables_list.txt
NSE_STOCK_LOAD/variables.py
nse_stock_load-2.0.dist-info/METADATA
nse_stock_load-2.0.dist-info/WHEEL
nse_stock_load-2.0.dist-info/entry_points.txt
nse_stock_load-2.0.dist-info/top_level.txt
nse_stock_load-2.0.dist-info/RECORD
