Metadata-Version: 2.1
Name: nse-stock-load
Version: 2.0
Summary: Package of load end to end nse data into mysql Database, corrected to_char to DATE_FORMAT
Author: kiran nanduri
Author-email: kirannanduri@outlook.com
License: kiran
Requires-Dist: SQLAlchemy ==1.4.14
Requires-Dist: numpy
Requires-Dist: pandas
Requires-Dist: requests ==2.25.1
